nemo_bo/__init__.py
nemo_bo/acquisition_functions/__init__.py
nemo_bo/acquisition_functions/base_acq_function.py
nemo_bo/acquisition_functions/expected_improvement/__init__.py
nemo_bo/acquisition_functions/expected_improvement/ehvi.py
nemo_bo/acquisition_functions/expected_improvement/expected_improvement.py
nemo_bo/acquisition_functions/highest_uncertainty/__init__.py
nemo_bo/acquisition_functions/highest_uncertainty/highest_uncertainty.py
nemo_bo/acquisition_functions/nsga_improvement/__init__.py
nemo_bo/acquisition_functions/nsga_improvement/genetic.py
nemo_bo/acquisition_functions/nsga_improvement/nsga2.py
nemo_bo/acquisition_functions/nsga_improvement/nsga3.py
nemo_bo/acquisition_functions/nsga_improvement/nsga_improvement.py
nemo_bo/acquisition_functions/nsga_improvement/problem_wrapper.py
nemo_bo/acquisition_functions/nsga_improvement/unsga3.py
nemo_bo/models/__init__.py
nemo_bo/models/base/__init__.py
nemo_bo/models/base/available_models.py
nemo_bo/models/base/base_model.py
nemo_bo/models/base/nn_save_checkpoint.py
nemo_bo/models/gp.py
nemo_bo/models/gp_gpytorch.py
nemo_bo/models/ngb.py
nemo_bo/models/nn_bayesian.py
nemo_bo/models/nn_concrete.py
nemo_bo/models/nn_ensemble.py
nemo_bo/models/rf.py
nemo_bo/models/xgb.py
nemo_bo/opt/__init__.py
nemo_bo/opt/benchmark.py
nemo_bo/opt/constraints.py
nemo_bo/opt/objectives.py
nemo_bo/opt/optimisation.py
nemo_bo/opt/samplers.py
nemo_bo/opt/utils_samplers/sampling.py
nemo_bo/opt/variables.py
nemo_bo/utils/__init__.py
nemo_bo/utils/data_proc.py
nemo_bo/utils/extract_excel.py
nemo_bo/utils/logger.py
nemo_bo/utils/perf_metrics.py
nemo_bo/utils/plotter.py
nemo_bo-0.1.16.dist-info/LICENSE
nemo_bo-0.1.16.dist-info/METADATA
nemo_bo-0.1.16.dist-info/WHEEL
nemo_bo-0.1.16.dist-info/RECORD
